regex2d/__init__.py
regex2d-0.1.0.dist-info/WHEEL
regex2d-0.1.0.dist-info/METADATA
regex2d-0.1.0.dist-info/RECORD
